teemboom_chat/__init__.py
teemboom_chat/token.py
teemboom_chat-1.0.0.dist-info/licenses/LICENSE
teemboom_chat-1.0.0.dist-info/METADATA
teemboom_chat-1.0.0.dist-info/WHEEL
teemboom_chat-1.0.0.dist-info/top_level.txt
teemboom_chat-1.0.0.dist-info/RECORD
